colorlogging/__init__.py
colorlogging/logger.py
ColorLogging-0.3.5.dist-info/METADATA
ColorLogging-0.3.5.dist-info/WHEEL
ColorLogging-0.3.5.dist-info/top_level.txt
ColorLogging-0.3.5.dist-info/RECORD
