Metadata-Version: 2.1
Name: ColorLogging
Version: 0.3.5
Summary: A simple Python logger with colored log levels
Home-page: http://github.com/tjkessler/ColorLogging
Author: Travis Kessler
Author-email: travis.j.kessler@gmail.com
License: MIT
Platform: UNKNOWN
Requires-Dist: colorama
